f2f/__init__.py
f2f/__version__.py
f2f/core/__init__.py
f2f/core/exceptions.py
f2f/core/onnx.py
f2f/detection/__init__.py
f2f/detection/s3fd/__init__.py
f2f/detection/s3fd/model.py
f2f/detection/s3fd/onnx.py
f2f/detection/scrfd/__init__.py
f2f/detection/scrfd/onnx.py
f2f/detection/utils/__init__.py
f2f/landmark/__init__.py
f2f/landmark/synthetic/__init__.py
f2f/landmark/synthetic/model.py
f2f/landmark/synthetic/onnx.py
f2f/mm/__init__.py
f2f/mm/flame/__init__.py
f2f/mm/flame/lbs.py
f2f/mm/flame/model.py
f2f/mm/flame/onnx.py
f2f/mm/flame/renderer.py
f2f/mm/flame/utils.py
f2f/mm/img2mm/__init__.py
f2f/mm/img2mm/deca/__init__.py
f2f/mm/img2mm/deca/deca.py
f2f/mm/img2mm/deca/emoca.py
f2f/mm/img2mm/deca/mica.py
f2f/mm/img2mm/deca/onnx.py
f2f/recognition/__init__.py
f2f/recognition/arcface/__init__.py
f2f/recognition/arcface/iresnet.py
f2f/recognition/arcface/model.py
f2f/segmentation/__init__.py
f2f/segmentation/bisenet/__init__.py
f2f/segmentation/bisenet/model.py
f2f/segmentation/bisenet/onnx.py
f2f/utils/__init__.py
f2f/utils/image.py
f2f/utils/np_ops.py
f2f/utils/onnx_ops.py
f2f/utils/transforms_np.py
f2f/utils/transforms_torch.py
face_to_face-0.4.1.dist-info/METADATA
face_to_face-0.4.1.dist-info/WHEEL
face_to_face-0.4.1.dist-info/top_level.txt
face_to_face-0.4.1.dist-info/RECORD
